{
    "copilot-vim": {
        "cargoLocks": null,
        "extract": null,
        "name": "copilot-vim",
        "passthru": null,
        "pinned": false,
        "src": {
            "deepClone": false,
            "fetchSubmodules": false,
            "leaveDotGit": false,
            "name": null,
            "owner": "github",
            "repo": "copilot.vim",
            "rev": "2f4f9259a5c0f927b31c4256cd3e4d7c6df87662",
            "sha256": "sha256-hUQhdIVIzHQKICYhSOjbG+GObxvpkub94fD4ESGwhmo=",
            "type": "github"
        },
        "version": "2f4f9259a5c0f927b31c4256cd3e4d7c6df87662"
    },
    "nvim-cokeline": {
        "cargoLocks": null,
        "extract": null,
        "name": "nvim-cokeline",
        "passthru": null,
        "pinned": false,
        "src": {
            "deepClone": false,
            "fetchSubmodules": false,
            "leaveDotGit": false,
            "name": null,
            "owner": "noib3",
            "repo": "nvim-cokeline",
            "rev": "501f93ec84af0d505d95d3827cad470b9c5e86dc",
            "sha256": "sha256-BQP4jOm55YeDfabsSdfEiRk2O7t7KARklSbyfBK5Zu0=",
            "type": "github"
        },
        "version": "501f93ec84af0d505d95d3827cad470b9c5e86dc"
    },
    "nvim-nu": {
        "cargoLocks": null,
        "extract": null,
        "name": "nvim-nu",
        "passthru": null,
        "pinned": false,
        "src": {
            "deepClone": false,
            "fetchSubmodules": false,
            "leaveDotGit": false,
            "name": null,
            "owner": "LhKipp",
            "repo": "nvim-nu",
            "rev": "94f237c219ae6bbb18e2f214783e0f1370eda27b",
            "sha256": "sha256-Ai2ot7d0TPQNDtY9Z/CPej5yJq7d6gZm1WJPW52L8/k=",
            "type": "github"
        },
        "version": "94f237c219ae6bbb18e2f214783e0f1370eda27b"
    },
    "openasar": {
        "cargoLocks": null,
        "extract": null,
        "name": "openasar",
        "passthru": null,
        "pinned": false,
        "src": {
            "deepClone": false,
            "fetchSubmodules": false,
            "leaveDotGit": false,
            "name": null,
            "owner": "GooseMod",
            "repo": "OpenAsar",
            "rev": "9582d791090b3f687e2c4351430fa42f8ccb36e1",
            "sha256": "sha256-DS03auE7uLOEGEY7PlF4w0FWPiyp5siALGK03GHl16M=",
            "type": "github"
        },
        "version": "9582d791090b3f687e2c4351430fa42f8ccb36e1"
    },
    "sddm": {
        "cargoLocks": null,
        "extract": null,
        "name": "sddm",
        "passthru": null,
        "pinned": false,
        "src": {
            "deepClone": false,
            "fetchSubmodules": false,
            "leaveDotGit": false,
            "name": null,
            "owner": "sddm",
            "repo": "sddm",
            "rev": "3e486499b9300ce8f9c62bd102e5119b27a2fad1",
            "sha256": "sha256-Y9WPm0MLWl/s0e0aoKKk0SSojqBrI/RdyxkgOz2Tk38=",
            "type": "github"
        },
        "version": "3e486499b9300ce8f9c62bd102e5119b27a2fad1"
    },
    "sddm-theme": {
        "cargoLocks": null,
        "extract": null,
        "name": "sddm-theme",
        "passthru": null,
        "pinned": false,
        "src": {
            "deepClone": false,
            "fetchSubmodules": false,
            "leaveDotGit": false,
            "name": null,
            "owner": "L4ki",
            "repo": "Dexy-Plasma-Themes",
            "rev": "7d308a296cd8313df6075677bd122580802e47bd",
            "sha256": "sha256-EyUX3t7IXD9lypkr2jcnwi72UxEd+rPbO76YJsbVu74=",
            "type": "github"
        },
        "version": "7d308a296cd8313df6075677bd122580802e47bd"
    },
    "zscroll": {
        "cargoLocks": null,
        "extract": null,
        "name": "zscroll",
        "passthru": null,
        "pinned": false,
        "src": {
            "deepClone": false,
            "fetchSubmodules": false,
            "leaveDotGit": false,
            "name": null,
            "owner": "noctuid",
            "repo": "zscroll",
            "rev": "abee462af9bc50f7ed17c36c32e55c356ac5c133",
            "sha256": "sha256-b9gQ11c2IOMx5sdpWhSxCnUPPZIbGMyBilsZYTF9TNw=",
            "type": "github"
        },
        "version": "abee462af9bc50f7ed17c36c32e55c356ac5c133"
    }
}